[
  {
    "nanoid": "OVN59PA5eqzvoQ",
    "name": "3ABN Kids Network",
    "stream_urls": [
      "https://3abn.bozztv.com/3abn2/Kids_live/smil:Kids_live.smil/playlist.m3u8"
    ],
    "youtube_urls": [],
    "languages": [
      "eng"
    ],
    "country": "us",
    "isGeoBlocked": false
  },
  {
    "nanoid": "yjR0KcAL5erp0S",
    "name": "ADN TV+",
    "stream_urls": [
      "https://d3b73b34o7cvkq.cloudfront.net/v1/master/3722c60a815c199d9c0ef36c5b73da68a62b09d1/cc-gz2sgqzp076kf/adn.m3u8"
    ],
    "youtube_urls": [],
    "languages": [
      "fra"
    ],
    "country": "fr",
    "isGeoBlocked": false
  },
  {
    "nanoid": "BDVUYXaNXNi52q",
    "name": "Amazing World of Gumball",
    "stream_urls": [],
    "youtube_urls": [
      "https://www.youtube-nocookie.com/embed/6dQnKVRq5s0"
    ],
    "languages": [
      "eng"
    ],
    "country": "uk",
    "isGeoBlocked": false
  },
  {
    "nanoid": "B6btjJsaGdIJVI",
    "name": "Ani-Blast",
    "stream_urls": [
      "https://amg19223-amg19223c9-amgplt0019.playout.now3.amagi.tv/playlist/amg19223-amg19223c9-amgplt0019/playlist.m3u8"
    ],
    "youtube_urls": [],
    "languages": [],
    "country": "hk",
    "isGeoBlocked": false
  },
  {
    "nanoid": "peEcGaZySDZRVf",
    "name": "Animation+",
    "stream_urls": [
      "https://pb-ioe9d0fpkd6pp.akamaized.net/playlist.m3u8"
    ],
    "youtube_urls": [],
    "languages": [
      "eng"
    ],
    "country": "us",
    "isGeoBlocked": true
  },
  {
    "nanoid": "BGpCMpAK7egFPE",
    "name": "Animax Asia India",
    "stream_urls": [
      "https://amg02159-kcglobal-amg02159c1-samsung-in-521.playouts.now.amagi.tv/playlist/amg02159-kcglobal-animax-samsungin/playlist.m3u8"
    ],
    "youtube_urls": [],
    "languages": [
      "jpn"
    ],
    "country": "sg",
    "isGeoBlocked": false
  },
  {
    "nanoid": "hkDzNHa7Mm4MEd",
    "name": "Anime Vision",
    "stream_urls": [
      "https://d1ujfw1zyymzyd.cloudfront.net/v1/master/3722c60a815c199d9c0ef36c5b73da68a62b09d1/cc-a6fukwkbxmex8/live/fast-channel-animevision-64527ec0/fast-channel-animevision-64527ec0.m3u8"
    ],
    "youtube_urls": [],
    "languages": [
      "spa"
    ],
    "country": "es",
    "isGeoBlocked": false
  },
  {
    "nanoid": "Zue327U2SxgoQE",
    "name": "Anime Vision Classics",
    "stream_urls": [
      "https://d82pyvmcw2kdc.cloudfront.net/v1/master/3722c60a815c199d9c0ef36c5b73da68a62b09d1/cc-swfivzrzwamaq/live/fast-channel-animevisionclassics-efc8dc6d/fast-channel-animevisionclassics-efc8dc6d.m3u8"
    ],
    "youtube_urls": [],
    "languages": [
      "spa"
    ],
    "country": "es",
    "isGeoBlocked": false
  },
  {
    "nanoid": "6jwIdmT15n1Yze",
    "name": "ANIME x HIDIVE",
    "stream_urls": [
      "https://d3f088nnrrvkwf.cloudfront.net/v1/amc_anime_x_hidive_1/samsungheadend_us/latest/main/hls/playlist.m3u8"
    ],
    "youtube_urls": [],
    "languages": [
      "eng"
    ],
    "country": "us",
    "isGeoBlocked": false
  },
  {
    "nanoid": "u2iS7uczBAriSJ",
    "name": "Aniplus Asia",
    "stream_urls": [
      "https://amg18481-amg18481c1-amgplt0352.playout.now3.amagi.tv/playlist/amg18481-amg18481c1-amgplt0352/playlist.m3u8"
    ],
    "youtube_urls": [],
    "languages": [
      "eng"
    ],
    "country": "sg",
    "isGeoBlocked": false
  },
  {
    "nanoid": "724JcFRQ3UIDmr",
    "name": "Aqua Teen Hunger Force",
    "stream_urls": [],
    "youtube_urls": [
      "https://www.youtube-nocookie.com/embed/KzCLOe4S_N0"
    ],
    "languages": [
      "eng"
    ],
    "country": "us",
    "isGeoBlocked": false
  },
  {
    "nanoid": "E3w7foWiEC1jDQ",
    "name": "Archie's Weird Mysteries",
    "stream_urls": [],
    "youtube_urls": [
      "https://www.youtube-nocookie.com/embed/z5kh_v4D2o8"
    ],
    "languages": [
      "eng"
    ],
    "country": "uk",
    "isGeoBlocked": false
  },
  {
    "nanoid": "6huapTHn6MUgAQ",
    "name": "Banijay Mr Bean Animé",
    "stream_urls": [
      "https://amg00627-amg00627c31-rakuten-fr-3991.playouts.now.amagi.tv/playlist/amg00627-banijayfast-mrbeanfrcc-rakutenfr/playlist.m3u8"
    ],
    "youtube_urls": [],
    "languages": [
      "fra"
    ],
    "country": "uk",
    "isGeoBlocked": false
  },
  {
    "nanoid": "fruS79xWb73ha2",
    "name": "Barney the Dinosaur",
    "stream_urls": [],
    "youtube_urls": [
      "https://www.youtube-nocookie.com/embed/p0Q5LwXmjUY"
    ],
    "languages": [
      "eng"
    ],
    "country": "ca",
    "isGeoBlocked": false
  },
  {
    "nanoid": "3zs2UMlidApgeb",
    "name": "Blues TV",
    "stream_urls": [
      "https://2-fss-2.streamhoster.com/pl_138/205510-3094608-1/playlist.m3u8"
    ],
    "youtube_urls": [],
    "languages": [
      "eng"
    ],
    "country": "us",
    "isGeoBlocked": false
  },
  {
    "nanoid": "77E2xhr3RrP82t",
    "name": "Cartoon Network Nederland",
    "stream_urls": [],
    "youtube_urls": [
      "https://www.youtube-nocookie.com/embed/xKqbuWWOFTs"
    ],
    "languages": [
      "nld"
    ],
    "country": "nl",
    "isGeoBlocked": false
  },
  {
    "nanoid": "P2Z68epVFispXu",
    "name": "Cartoon Network Polska",
    "stream_urls": [],
    "youtube_urls": [
      "https://www.youtube-nocookie.com/embed/G9hx5Al3vxM"
    ],
    "languages": [
      "pol"
    ],
    "country": "pl",
    "isGeoBlocked": false
  },
  {
    "nanoid": "QwrXrJ43PZBFLz",
    "name": "Cartoon Network România",
    "stream_urls": [],
    "youtube_urls": [
      "https://www.youtube-nocookie.com/embed/5e31prxEol0"
    ],
    "languages": [
      "ron"
    ],
    "country": "ro",
    "isGeoBlocked": false
  },
  {
    "nanoid": "tIGqdwnTT3ZqJq",
    "name": "Cartoon Network: Adventure Time",
    "stream_urls": [],
    "youtube_urls": [
      "https://www.youtube-nocookie.com/embed/uZkaJ3e9nfY"
    ],
    "languages": [
      "eng"
    ],
    "country": "us",
    "isGeoBlocked": false
  },
  {
    "nanoid": "okFgL1Lb78hUrK",
    "name": "Cartoon Network: We Bear Bears",
    "stream_urls": [],
    "youtube_urls": [
      "https://www.youtube-nocookie.com/embed/RXoDbwZmXV8"
    ],
    "languages": [
      "eng"
    ],
    "country": "sg",
    "isGeoBlocked": false
  },
  {
    "nanoid": "dS38RFG3Xj3JOv",
    "name": "CONtv: Yu-Gi-Oh! (Deutsch)",
    "stream_urls": [],
    "youtube_urls": [
      "https://www.youtube-nocookie.com/embed/eNvXmPBLOpg"
    ],
    "languages": [
      "deu"
    ],
    "country": "us",
    "isGeoBlocked": false
  },
  {
    "nanoid": "5uaACATXkoGQ0l",
    "name": "CONtv: Yu-Gi-Oh! Duel Monsters (Español)",
    "stream_urls": [],
    "youtube_urls": [
      "https://www.youtube-nocookie.com/embed/HZeBHEc7voU"
    ],
    "languages": [
      "spa"
    ],
    "country": "us",
    "isGeoBlocked": false
  },
  {
    "nanoid": "8oBrseq395AJ47",
    "name": "CONtv: Yu-Gi-Oh! GX (English)",
    "stream_urls": [],
    "youtube_urls": [
      "https://www.youtube-nocookie.com/embed/hSHx9EhMBn0"
    ],
    "languages": [
      "eng"
    ],
    "country": "us",
    "isGeoBlocked": false
  },
  {
    "nanoid": "xhpSHNk65C34T5",
    "name": "Disney Channel: Gravity Falls",
    "stream_urls": [],
    "youtube_urls": [
      "https://www.youtube-nocookie.com/embed/eE1L08hNdW8"
    ],
    "languages": [
      "eng"
    ],
    "country": "us",
    "isGeoBlocked": false
  },
  {
    "nanoid": "9Vi7dWXxMFcp0J",
    "name": "Disney Jr. Latin America South",
    "stream_urls": [
      "https://tr.live.clarovtrcdn.vtrplay.com/disneyjrhdchi/vxfmt=dp/playlist.m3u8?device_profile=STB_HLS_VCAS_LIVE_HD"
    ],
    "youtube_urls": [],
    "languages": [
      "spa"
    ],
    "country": "ar",
    "isGeoBlocked": false
  },
  {
    "nanoid": "LRgPxcQZ9T6wh6",
    "name": "EnerGeek",
    "stream_urls": [
      "https://backend.energeek.cl/webtv/egretroweb/index.m3u8?token=ZZDemoIPTVGH"
    ],
    "youtube_urls": [],
    "languages": [
      "spa"
    ],
    "country": "cl",
    "isGeoBlocked": false
  },
  {
    "nanoid": "Fho666tDNHtuPI",
    "name": "EnerGeek Fan",
    "stream_urls": [
      "https://backend.energeek.cl/webtv/egfanweb/index.m3u8?token=ZZDemoIPTVGH"
    ],
    "youtube_urls": [],
    "languages": [
      "spa"
    ],
    "country": "cl",
    "isGeoBlocked": false
  },
  {
    "nanoid": "ejJZfMgOR7K5m8",
    "name": "Extrema Kids TV",
    "stream_urls": [
      "https://627bb251f23c7.streamlock.net:444/ExtremaKids/ExtremaKids/playlist.m3u8"
    ],
    "youtube_urls": [],
    "languages": [
      "spa"
    ],
    "country": "cr",
    "isGeoBlocked": false
  },
  {
    "nanoid": "c4f5dB2f1HZXBV",
    "name": "FilmRise Anime",
    "stream_urls": [
      "https://dvu7aia8rjlfm.cloudfront.net/master.m3u8"
    ],
    "youtube_urls": [],
    "languages": [
      "eng"
    ],
    "country": "us",
    "isGeoBlocked": false
  },
  {
    "nanoid": "oj7vX3xxxcxlj0",
    "name": "Fugget About It",
    "stream_urls": [],
    "youtube_urls": [
      "https://www.youtube-nocookie.com/embed/4HD4A6b32ZU"
    ],
    "languages": [
      "eng"
    ],
    "country": "ca",
    "isGeoBlocked": false
  },
  {
    "nanoid": "BHktLaXb4NGD72",
    "name": "Gong",
    "stream_urls": [
      "https://amg01596-gongnetworks-gong-ono-vh5f2.amagi.tv/1080p-vtt/index.m3u8"
    ],
    "youtube_urls": [],
    "languages": [
      "fra"
    ],
    "country": "fr",
    "isGeoBlocked": false
  },
  {
    "nanoid": "Ys1fR7qaVevN2A",
    "name": "Gumball",
    "stream_urls": [],
    "youtube_urls": [
      "https://www.youtube-nocookie.com/embed/IT1IZpY7uzA"
    ],
    "languages": [
      "ara"
    ],
    "country": "sa",
    "isGeoBlocked": false
  },
  {
    "nanoid": "5YtwjYlglp4KTy",
    "name": "Gumball",
    "stream_urls": [],
    "youtube_urls": [
      "https://www.youtube-nocookie.com/embed/9LDR3lHACKM"
    ],
    "languages": [
      "tur"
    ],
    "country": "tr",
    "isGeoBlocked": false
  },
  {
    "nanoid": "6LMZLvrPTalkLd",
    "name": "Hasbro Pulse: Transformers Gen 1",
    "stream_urls": [],
    "youtube_urls": [
      "https://www.youtube-nocookie.com/embed/YGbsgUXdelE"
    ],
    "languages": [
      "eng"
    ],
    "country": "us",
    "isGeoBlocked": false
  },
  {
    "nanoid": "0ivoQLrHJOMC00",
    "name": "Hasbro Pulse: Transformers Generation 1",
    "stream_urls": [],
    "youtube_urls": [
      "https://www.youtube-nocookie.com/embed/aTCYFcsbsxo"
    ],
    "languages": [
      "eng"
    ],
    "country": "us",
    "isGeoBlocked": false
  },
  {
    "nanoid": "dLuyF7ipbY6e1u",
    "name": "Hasbro: G.I. JOE",
    "stream_urls": [],
    "youtube_urls": [
      "https://www.youtube-nocookie.com/embed/TZ3mxF4U__k"
    ],
    "languages": [
      "eng"
    ],
    "country": "us",
    "isGeoBlocked": false
  },
  {
    "nanoid": "VVVtm9fLhy7n1l",
    "name": "Hasbro: Power Rangers",
    "stream_urls": [],
    "youtube_urls": [
      "https://www.youtube-nocookie.com/embed/Fl-WGssGnak"
    ],
    "languages": [
      "eng"
    ],
    "country": "us",
    "isGeoBlocked": false
  },
  {
    "nanoid": "1ov4rKCt7xdyVW",
    "name": "Japanim TV",
    "stream_urls": [
      "https://foxkidstv.be:3369/stream/play.m3u8"
    ],
    "youtube_urls": [],
    "languages": [
      "fra"
    ],
    "country": "be",
    "isGeoBlocked": false
  },
  {
    "nanoid": "6uP6CNEGYjRRQY",
    "name": "Kanade",
    "stream_urls": [
      "https://backend.energeek.cl/webtv/kanadeweb/index.m3u8?token=ZZDemoIPTVGH"
    ],
    "youtube_urls": [],
    "languages": [
      "spa"
    ],
    "country": "cl",
    "isGeoBlocked": false
  },
  {
    "nanoid": "KFX8r91Rf69oJB",
    "name": "Kapitan Bomba",
    "stream_urls": [],
    "youtube_urls": [
      "https://www.youtube-nocookie.com/embed/OfUHOCXXVxw"
    ],
    "languages": [
      "pol"
    ],
    "country": "pl",
    "isGeoBlocked": false
  },
  {
    "nanoid": "Mi17BkbSFMtULi",
    "name": "Kuriakos Kids",
    "stream_urls": [
      "https://w2.manasat.com/kkids/smil:kkids.smil/playlist.m3u8"
    ],
    "youtube_urls": [],
    "languages": [
      "por"
    ],
    "country": "pt",
    "isGeoBlocked": false
  },
  {
    "nanoid": "dValMPk4YLHMz4",
    "name": "Marvel HQ: Marvel's Avengers Assemble",
    "stream_urls": [],
    "youtube_urls": [
      "https://www.youtube-nocookie.com/embed/7oPYfe03bCs"
    ],
    "languages": [
      "eng"
    ],
    "country": "us",
    "isGeoBlocked": false
  },
  {
    "nanoid": "HMnAQkRBUvy7iD",
    "name": "Marvel HQ: Marvel's Future Avengers",
    "stream_urls": [],
    "youtube_urls": [
      "https://www.youtube-nocookie.com/embed/yABPtUc7KOg"
    ],
    "languages": [
      "eng"
    ],
    "country": "us",
    "isGeoBlocked": false
  },
  {
    "nanoid": "DdiVuOolojZUS0",
    "name": "MCN6 Music Channel",
    "stream_urls": [
      "https://d18fcxaqfnwjhj.cloudfront.net/CDN_Ingest/MCN6_MUSIC.smil/Playlist.m3u8"
    ],
    "youtube_urls": [],
    "languages": [
      "eng"
    ],
    "country": "us",
    "isGeoBlocked": false
  },
  {
    "nanoid": "R6VpE6L98QcSep",
    "name": "Mr. Bean Animated",
    "stream_urls": [
      "https://d2t1w90tnft92.cloudfront.net/Mr_Bean_Animated.m3u8"
    ],
    "youtube_urls": [],
    "languages": [
      "eng"
    ],
    "country": "uk",
    "isGeoBlocked": false
  },
  {
    "nanoid": "suq6mp1ymDEDbo",
    "name": "Mr. Bean Anime Italy",
    "stream_urls": [
      "https://amg00627-amg00627c29-rakuten-it-3989.playouts.now.amagi.tv/playlist/amg00627-banijayfast-mrbeanitcc-rakutenit/playlist.m3u8"
    ],
    "youtube_urls": [],
    "languages": [
      "ita"
    ],
    "country": "uk",
    "isGeoBlocked": false
  },
  {
    "nanoid": "kz39SbfxEaAf4G",
    "name": "Mr. Bean Anime Spain",
    "stream_urls": [
      "https://amg00627-amg00627c30-rakuten-es-3990.playouts.now.amagi.tv/playlist/amg00627-banijayfast-mrbeanescc-rakutenes/playlist.m3u8"
    ],
    "youtube_urls": [],
    "languages": [
      "spa"
    ],
    "country": "uk",
    "isGeoBlocked": false
  },
  {
    "nanoid": "nr7YB5evIv8hrR",
    "name": "Naruto",
    "stream_urls": [
      "https://d21vn5eki5qsdi.cloudfront.net/playlist.m3u8"
    ],
    "youtube_urls": [],
    "languages": [
      "eng"
    ],
    "country": "us",
    "isGeoBlocked": false
  },
  {
    "nanoid": "F7h50bZe1CVuSg",
    "name": "NickOnline Feed 2",
    "stream_urls": [
      "https://x1co.com.br:2083/hls/stream.m3u8"
    ],
    "youtube_urls": [],
    "languages": [
      "por"
    ],
    "country": "br",
    "isGeoBlocked": false
  },
  {
    "nanoid": "B7oUuXqbWsfBhP",
    "name": "OGGY",
    "stream_urls": [],
    "youtube_urls": [
      "https://www.youtube-nocookie.com/embed/n4lcJjsMEb0"
    ],
    "languages": [
      "eng"
    ],
    "country": "fr",
    "isGeoBlocked": false
  },
  {
    "nanoid": "yzZp6BhMvaS7qt",
    "name": "PJ Masks Brasil",
    "stream_urls": [],
    "youtube_urls": [
      "https://www.youtube-nocookie.com/embed/aKtUWVDW10E"
    ],
    "languages": [
      "por"
    ],
    "country": "br",
    "isGeoBlocked": false
  },
  {
    "nanoid": "oubeKLPS2AIZdf",
    "name": "Pro100TV",
    "stream_urls": [
      "https://sirius.greenhosting.ru/Pro100tvRu/video.m3u8"
    ],
    "youtube_urls": [],
    "languages": [
      "rus"
    ],
    "country": "ru",
    "isGeoBlocked": false
  },
  {
    "nanoid": "Br53BhiHjkS3op",
    "name": "RetroCrush",
    "stream_urls": [
      "https://linear-899.frequency.stream/dist/cineverse/899/hls/master/playlist.m3u8",
      "https://d2nqmwm1ndpgi2.cloudfront.net/playlist.m3u8"
    ],
    "youtube_urls": [],
    "languages": [
      "eng"
    ],
    "country": "us",
    "isGeoBlocked": false
  },
  {
    "nanoid": "8LKXkhcjKmXHN8",
    "name": "Rick and Morty",
    "stream_urls": [],
    "youtube_urls": [
      "https://www.youtube-nocookie.com/embed/iiRNq1sxr0U"
    ],
    "languages": [
      "eng"
    ],
    "country": "uk",
    "isGeoBlocked": false
  },
  {
    "nanoid": "P0LU27eSLAz1HY",
    "name": "Shout! Studios: Speed Racer",
    "stream_urls": [],
    "youtube_urls": [
      "https://www.youtube-nocookie.com/embed/1E6e_vkbJQ0"
    ],
    "languages": [
      "eng"
    ],
    "country": "us",
    "isGeoBlocked": false
  },
  {
    "nanoid": "pApkFb67wcPTJl",
    "name": "Soviet Toons: Ну, погоди!",
    "stream_urls": [],
    "youtube_urls": [
      "https://www.youtube-nocookie.com/embed/TfS3DD_ELc0"
    ],
    "languages": [
      "rus"
    ],
    "country": "uk",
    "isGeoBlocked": false
  },
  {
    "nanoid": "yua0MMLiJjjDoi",
    "name": "Talking Tom & Friends TV: Garfield",
    "stream_urls": [],
    "youtube_urls": [
      "https://www.youtube-nocookie.com/embed/oV5gVoZQ7xU"
    ],
    "languages": [
      "eng"
    ],
    "country": "us",
    "isGeoBlocked": false
  },
  {
    "nanoid": "Ul1MxG7pzChnBN",
    "name": "Teenage Mutant Ninja Turtles: TMNT",
    "stream_urls": [],
    "youtube_urls": [
      "https://www.youtube-nocookie.com/embed/RMClXrXrDWU"
    ],
    "languages": [
      "eng"
    ],
    "country": "us",
    "isGeoBlocked": false
  },
  {
    "nanoid": "7ou9OY1nQUGsSq",
    "name": "Tiguerito TV",
    "stream_urls": [
      "https://ss2.tvrdomi.com:1936/tigueritostv/tigueritostv/playlist.m3u8"
    ],
    "youtube_urls": [],
    "languages": [
      "spa"
    ],
    "country": "do",
    "isGeoBlocked": false
  },
  {
    "nanoid": "vxuvNL1pu9DfjK",
    "name": "TokuSHOUTsu: Speed Racer",
    "stream_urls": [],
    "youtube_urls": [
      "https://www.youtube-nocookie.com/embed/qt32SoWwpMQ"
    ],
    "languages": [
      "eng"
    ],
    "country": "us",
    "isGeoBlocked": false
  },
  {
    "nanoid": "BUo7XkGZxD8OQU",
    "name": "Total Drama: All Stars",
    "stream_urls": [],
    "youtube_urls": [
      "https://www.youtube-nocookie.com/embed/GpK-98J0bdA"
    ],
    "languages": [
      "eng"
    ],
    "country": "ca",
    "isGeoBlocked": false
  },
  {
    "nanoid": "f7xu4xx77esq0e",
    "name": "Total Drama: The Ridonculous Race",
    "stream_urls": [],
    "youtube_urls": [
      "https://www.youtube-nocookie.com/embed/vr1Uu9y6SHk"
    ],
    "languages": [
      "eng"
    ],
    "country": "ca",
    "isGeoBlocked": false
  },
  {
    "nanoid": "Vb412LOIWSgJdP",
    "name": "Total Drama: World Tour",
    "stream_urls": [],
    "youtube_urls": [
      "https://www.youtube-nocookie.com/embed/UBaxq2b6F6M"
    ],
    "languages": [
      "eng"
    ],
    "country": "ca",
    "isGeoBlocked": false
  },
  {
    "nanoid": "Tp12tSjO1JEHMH",
    "name": "Total Dramarama",
    "stream_urls": [],
    "youtube_urls": [
      "https://www.youtube-nocookie.com/embed/G6XKGQWJIFk"
    ],
    "languages": [
      "eng"
    ],
    "country": "ca",
    "isGeoBlocked": false
  },
  {
    "nanoid": "tmleCZATQa5PCa",
    "name": "Universal Jr: Team Mekbots",
    "stream_urls": [],
    "youtube_urls": [
      "https://www.youtube-nocookie.com/embed/ilcJNw1SToA"
    ],
    "languages": [
      "eng"
    ],
    "country": "us",
    "isGeoBlocked": false
  },
  {
    "nanoid": "hzA9M1g8Uiyjea",
    "name": "Xtrema Cartoons",
    "stream_urls": [
      "https://stmv6.voxtvhd.com.br/xtremacartoons/xtremacartoons/playlist.m3u8"
    ],
    "youtube_urls": [],
    "languages": [
      "spa"
    ],
    "country": "ar",
    "isGeoBlocked": false
  },
  {
    "nanoid": "1pTOFnPJCFs4Na",
    "name": "Yu-Gi-Oh!",
    "stream_urls": [
      "https://amg01796-amg01796c19-rakuten-gb-7486.playouts.now.amagi.tv/playlist/amg01796-fastmediafast-yugioh2en-rakutengb/playlist.m3u8",
      "https://dwgcgcahlni2h.cloudfront.net/playlist.m3u8"
    ],
    "youtube_urls": [],
    "languages": [
      "eng"
    ],
    "country": "us",
    "isGeoBlocked": false
  },
  {
    "nanoid": "gJChs4RXWcqghm",
    "name": "Мультимания",
    "stream_urls": [
      "https://sirius.greenhosting.ru/MultimaniaRu/tracks-v1a1/mono.m3u8",
      "https://sirius.greenhosting.ru/MultimaniaRu/video.m3u8"
    ],
    "youtube_urls": [],
    "languages": [
      "rus"
    ],
    "country": "ru",
    "isGeoBlocked": false
  },
  {
    "nanoid": "MCj2Vyne0bnAk3",
    "name": "Пингвин",
    "stream_urls": [
      "https://sirius.greenhosting.ru/PingvinRu/video.m3u8"
    ],
    "youtube_urls": [],
    "languages": [
      "lav"
    ],
    "country": "lv",
    "isGeoBlocked": false
  },
  {
    "nanoid": "9Uizi8HMPFF6Ku",
    "name": "Солнце",
    "stream_urls": [
      "https://tv.mediacdn.ru/live/solntse/playlist.m3u8",
      "https://zabava-htlive.cdn.ngenix.net/hls/CH_DISNEY/variant.m3u8"
    ],
    "youtube_urls": [],
    "languages": [
      "rus"
    ],
    "country": "ru",
    "isGeoBlocked": false
  }
]
