[
  {
    "nanoid": "UyP5uli9gNPXtq",
    "name": "A Spor",
    "stream_urls": [],
    "youtube_urls": [
      "https://www.youtube-nocookie.com/embed/mgeW8Qm8-SY"
    ],
    "languages": [
      "tur"
    ],
    "country": "tr",
    "isGeoBlocked": false
  },
  {
    "nanoid": "v9zxgiBZu0T9zY",
    "name": "ACCDN",
    "stream_urls": [
      "https://raycom-accdn-firetv.amagi.tv/playlist.m3u8",
      "https://d53csymoczzde.cloudfront.net/ACC_Digital_Network.m3u8",
      "https://aegis-cloudfront-1.tubi.video/a1e671ae-d1c2-4e39-99c7-889e83056fd2/playlist.m3u8"
    ],
    "youtube_urls": [],
    "languages": [
      "eng"
    ],
    "country": "us",
    "isGeoBlocked": false
  },
  {
    "nanoid": "AxkHU8DJYXqb2o",
    "name": "ACI Sport TV",
    "stream_urls": [
      "https://webstream.multistream.it/memfs/e2cb3629-c1a2-495b-b43a-9eb386f04ed8.m3u8"
    ],
    "youtube_urls": [],
    "languages": [
      "ita"
    ],
    "country": "it",
    "isGeoBlocked": false
  },
  {
    "nanoid": "EgspbzPRaIJYXi",
    "name": "ADO TV",
    "stream_urls": [
      "https://strhls.streamakaci.tv/ortb/ortb2-multi/playlist.m3u8"
    ],
    "youtube_urls": [],
    "languages": [
      "fra"
    ],
    "country": "bj",
    "isGeoBlocked": false
  },
  {
    "nanoid": "FsR4OMNuaQ7RDi",
    "name": "Africa 24 Sport",
    "stream_urls": [
      "https://africa24.vedge.infomaniak.com/livecast/ik:africa24sport/manifest.m3u8"
    ],
    "youtube_urls": [],
    "languages": [
      "fra"
    ],
    "country": "fr",
    "isGeoBlocked": false
  },
  {
    "nanoid": "xNO3EJp4mhTrDD",
    "name": "AS3 Sport TV",
    "stream_urls": [
      "https://streamtv.as3sport.online:3394/hybrid/play.m3u8"
    ],
    "youtube_urls": [],
    "languages": [
      "spa"
    ],
    "country": "ve",
    "isGeoBlocked": false
  },
  {
    "nanoid": "v8Zzxjpx6SD9DW",
    "name": "ATG Live",
    "stream_urls": [
      "https://kanal75xto-llhls.akamaized.net/live/Data/atg-kanal-15-02a-rr/HLS-Legacy-HL/atg-kanal-15-02a-rr.m3u8"
    ],
    "youtube_urls": [],
    "languages": [
      "swe"
    ],
    "country": "se",
    "isGeoBlocked": false
  },
  {
    "nanoid": "YFqOd9RFAP2HGq",
    "name": "Bahrain Sports 1",
    "stream_urls": [
      "https://5c7b683162943.streamlock.net/live/ngrp:sportsone_all/playlist.m3u8"
    ],
    "youtube_urls": [],
    "languages": [
      "ara"
    ],
    "country": "bh",
    "isGeoBlocked": false
  },
  {
    "nanoid": "SBDiIYv6gMiZbW",
    "name": "Bahrain Sports 2",
    "stream_urls": [
      "https://5c7b683162943.streamlock.net/live/ngrp:bahrainsportstwo_all/playlist.m3u8"
    ],
    "youtube_urls": [],
    "languages": [
      "ara"
    ],
    "country": "bh",
    "isGeoBlocked": false
  },
  {
    "nanoid": "ryl2lCtBRetuci",
    "name": "beIN SPORTS Türkiye",
    "stream_urls": [],
    "youtube_urls": [
      "https://www.youtube-nocookie.com/embed/i7UpPgxfZZ8"
    ],
    "languages": [
      "tur"
    ],
    "country": "tr",
    "isGeoBlocked": false
  },
  {
    "nanoid": "38wfpfuPiROwg3",
    "name": "BEK TV Sports West",
    "stream_urls": [
      "https://cdn3.wowza.com/5/ZWQ1K2NYTmpFbGsr/BEK-WOWZA-1/smil:BEKPRIMEW.smil/playlist.m3u8"
    ],
    "youtube_urls": [],
    "languages": [
      "eng"
    ],
    "country": "us",
    "isGeoBlocked": false
  },
  {
    "nanoid": "M4nYho03XLslkh",
    "name": "Billiard TV",
    "stream_urls": [
      "https://1621590671.rsc.cdn77.org/HLS/BILLIARDTV.m3u8",
      "https://pb-wm04vonaerv0k.akamaized.net/billi.m3u8"
    ],
    "youtube_urls": [],
    "languages": [
      "eng"
    ],
    "country": "us",
    "isGeoBlocked": true
  },
  {
    "nanoid": "haAQVTXfQJECVE",
    "name": "CazeTV (1080i)",
    "stream_urls": [
      "https://dfr80qz435crc.cloudfront.net/MNOP/Amagi/Caze/Caze_TV_BR/Caze_TV.m3u8"
    ],
    "youtube_urls": [],
    "languages": [
      "por"
    ],
    "country": "br",
    "isGeoBlocked": false
  },
  {
    "nanoid": "Mut1mafEBDelBc",
    "name": "CBS Sports Golazo Network",
    "stream_urls": [
      "https://proped3fhg87.airspace-cdn.cbsivideo.com/golazo-live-dai/master/golazo-live-dai.m3u8"
    ],
    "youtube_urls": [],
    "languages": [
      "eng"
    ],
    "country": "us",
    "isGeoBlocked": false
  },
  {
    "nanoid": "BVjIUopeFkeF0s",
    "name": "CBS Sports HQ",
    "stream_urls": [
      "https://propee33f9c2.airspace-cdn.cbsivideo.com/index.m3u8"
    ],
    "youtube_urls": [],
    "languages": [
      "eng"
    ],
    "country": "us",
    "isGeoBlocked": true
  },
  {
    "nanoid": "eR1xoR8d2AHyV1",
    "name": "DAZN Combat",
    "stream_urls": [
      "https://dazn-combat-rakuten.amagi.tv/hls/amagi_hls_data_rakutenAA-dazn-combat-rakuten/CDN/master.m3u8"
    ],
    "youtube_urls": [],
    "languages": [
      "eng"
    ],
    "country": "uk",
    "isGeoBlocked": false
  },
  {
    "nanoid": "44h9Z4ZEgtGb2n",
    "name": "DD Sports SD",
    "stream_urls": [
      "https://d3qs3d2rkhfqrt.cloudfront.net/out/v1/b17adfe543354fdd8d189b110617cddd/index.m3u8",
      "https://cdn-6.pishow.tv/live/13/master.m3u8"
    ],
    "youtube_urls": [],
    "languages": [
      "hin"
    ],
    "country": "in",
    "isGeoBlocked": false
  },
  {
    "nanoid": "KGBMTUYjkdpD8D",
    "name": "DraftKings Network",
    "stream_urls": [
      "https://na.linear.zype.com/e0bd0e23-a958-4e43-8164-4f2fef8876a8/fd3614bd-90bf-4530-a277-65ae3a1720c8-zype/live.m3u8",
      "https://d2obyvq5go60aw.cloudfront.net/DraftKings_Network.m3u8"
    ],
    "youtube_urls": [],
    "languages": [
      "eng"
    ],
    "country": "us",
    "isGeoBlocked": false
  },
  {
    "nanoid": "NOygrZkydmJ7CX",
    "name": "Enduro Life Media",
    "stream_urls": [],
    "youtube_urls": [
      "https://www.youtube-nocookie.com/embed/TrYl7woH7wE"
    ],
    "languages": [
      "eng"
    ],
    "country": "uk",
    "isGeoBlocked": false
  },
  {
    "nanoid": "FCUxtK6sDPDHUw",
    "name": "ESPN8 The Ocho",
    "stream_urls": [
      "https://d3b6q2ou5kp8ke.cloudfront.net/ESPNTheOcho.m3u8"
    ],
    "youtube_urls": [],
    "languages": [
      "eng"
    ],
    "country": "us",
    "isGeoBlocked": false
  },
  {
    "nanoid": "BkNvZNcvt4fu9h",
    "name": "F1 Channel",
    "stream_urls": [
      "https://amg12058-c15studio-amg12058c1-lg-us-5787.playouts.now.amagi.tv/playlist.m3u8"
    ],
    "youtube_urls": [],
    "languages": [
      "eng"
    ],
    "country": "ie",
    "isGeoBlocked": false
  },
  {
    "nanoid": "kDBBY14O2KzLCz",
    "name": "FanDuel Racing",
    "stream_urls": [
      "https://d3ehq1uaxory6w.cloudfront.net/out/v1/35c05f080f4e49a4b4eb031b5a14e505/TVG2index_2.m3u8"
    ],
    "youtube_urls": [],
    "languages": [
      "eng"
    ],
    "country": "us",
    "isGeoBlocked": false
  },
  {
    "nanoid": "v3omHpUDGpBh5v",
    "name": "FanDuel TV",
    "stream_urls": [
      "https://d2jl8r92tdc3f1.cloudfront.net/out/v1/59419700344b4625b7cb0693ba265ea3/TVGindex_1.m3u8"
    ],
    "youtube_urls": [],
    "languages": [
      "eng"
    ],
    "country": "us",
    "isGeoBlocked": false
  },
  {
    "nanoid": "SSm48TGJZ2ZZyq",
    "name": "FB TV",
    "stream_urls": [
      "https://1hskrdto.rocketcdn.com/fenerbahcetv.smil/playlist.m3u8"
    ],
    "youtube_urls": [],
    "languages": [
      "tur"
    ],
    "country": "tr",
    "isGeoBlocked": false
  },
  {
    "nanoid": "tmxui0c8hzZyDz",
    "name": "FIFA+",
    "stream_urls": [
      "https://d2w9q46ikgrcwx.cloudfront.net/v1/sysdata_s_p_a_fifa_7/samsungheadend_us/latest/main/hls/playlist.m3u8"
    ],
    "youtube_urls": [],
    "languages": [
      "eng"
    ],
    "country": "uk",
    "isGeoBlocked": false
  },
  {
    "nanoid": "LRBUacm9msNRQ8",
    "name": "Fight Network",
    "stream_urls": [
      "https://amg00966-amg00966c10-amgplt0081.playout.now3.amagi.tv/playlist/amg00966-amg00966c10-amgplt0081/playlist.m3u8",
      "https://a-cdn.klowdtv.com/live2/fight_720p/playlist.m3u8"
    ],
    "youtube_urls": [],
    "languages": [
      "eng"
    ],
    "country": "ca",
    "isGeoBlocked": false
  },
  {
    "nanoid": "9Ji1RIoUGeL46E",
    "name": "FITE 24/7",
    "stream_urls": [
      "https://d3d85c7qkywguj.cloudfront.net/v1/master/9d062541f2ff39b5c0f48b743c6411d25f62fc25/FiteTV-DistroTV/263.m3u8?ads.vf=d4xngnNL060",
      "https://d3d85c7qkywguj.cloudfront.net/scheduler/scheduleMaster/263.m3u8",
      "https://a-cdn.klowdtv.com/live2/fite247_720p/playlist.m3u8"
    ],
    "youtube_urls": [],
    "languages": [
      "eng"
    ],
    "country": "us",
    "isGeoBlocked": false
  },
  {
    "nanoid": "3XWzDx4FnKV7NI",
    "name": "Fox Sports en Espanol",
    "stream_urls": [
      "https://live-manifest.production-public.tubi.io/live/d906efca-1302-4e29-b0d9-9a1d7a305d69/playlist.m3u8"
    ],
    "youtube_urls": [],
    "languages": [
      "spa"
    ],
    "country": "us",
    "isGeoBlocked": false
  },
  {
    "nanoid": "KKtmG6U0zua4oT",
    "name": "FTF Sports",
    "stream_urls": [
      "https://1657061170.rsc.cdn77.org/HLS/FTF-LINEAR.m3u8"
    ],
    "youtube_urls": [],
    "languages": [
      "eng"
    ],
    "country": "us",
    "isGeoBlocked": false
  },
  {
    "nanoid": "4r0QKfGoGD09Z7",
    "name": "FTV",
    "stream_urls": [
      "https://master.tucableip.com/ftvhd/index.m3u8"
    ],
    "youtube_urls": [],
    "languages": [
      "spa"
    ],
    "country": "bo",
    "isGeoBlocked": false
  },
  {
    "nanoid": "rSbwbBDpFexSew",
    "name": "fubo Sports Network",
    "stream_urls": [
      "https://aegis-cloudfront-1.tubi.video/c2ac89da-5c69-439e-b85d-d87de0548b54/playlist.m3u8"
    ],
    "youtube_urls": [],
    "languages": [
      "eng"
    ],
    "country": "us",
    "isGeoBlocked": true
  },
  {
    "nanoid": "dsBKZyQRGT7j8N",
    "name": "Fuel TV",
    "stream_urls": [
      "https://amg01074-fueltv-fueltvnz-samsungnz-i8ani.amagi.tv/playlist/amg01074-fueltv-fueltvnz-samsungnz/playlist.m3u8",
      "https://amg01074-fueltv-amg01074c1-stirr-us-4214.playouts.now.amagi.tv/playlist.m3u8",
      "https://amg01074-fueltv-amg01074c1-firetv-us-3150.playouts.now.amagi.tv/playlist.m3u8"
    ],
    "youtube_urls": [],
    "languages": [
      "eng"
    ],
    "country": "pt",
    "isGeoBlocked": false
  },
  {
    "nanoid": "440EBhNILeBYuU",
    "name": "Futbol",
    "stream_urls": [
      "https://live.teleradiocom.tj/8/3m.m3u8"
    ],
    "youtube_urls": [],
    "languages": [
      "tgk"
    ],
    "country": "tj",
    "isGeoBlocked": false
  },
  {
    "nanoid": "3PWIwG9FFIlO5Y",
    "name": "Game+",
    "stream_urls": [
      "https://a-cdn.klowdtv.com/live2/fntsy_720p/playlist.m3u8"
    ],
    "youtube_urls": [],
    "languages": [
      "eng"
    ],
    "country": "ca",
    "isGeoBlocked": false
  },
  {
    "nanoid": "kM3B5XM0dLyl7Z",
    "name": "GEM Fit",
    "stream_urls": [
      "https://ca-rt.onetv.app/gemfit/index-0.m3u8?token=onetv202"
    ],
    "youtube_urls": [],
    "languages": [
      "fas"
    ],
    "country": "tr",
    "isGeoBlocked": false
  },
  {
    "nanoid": "GZWR4WKfwfXc9w",
    "name": "Gol Classics",
    "stream_urls": [
      "https://d71gqtnep83vb.cloudfront.net/gol_classics/gol_classics.m3u8"
    ],
    "youtube_urls": [],
    "languages": [
      "spa"
    ],
    "country": "es",
    "isGeoBlocked": false
  },
  {
    "nanoid": "bhT3j01Nh3aRCQ",
    "name": "Hard Knocks",
    "stream_urls": [
      "https://d3uyzhwvmemdyf.cloudfront.net/v1/master/9d062541f2ff39b5c0f48b743c6411d25f62fc25/HardKnocks-PLEX/121.m3u8"
    ],
    "youtube_urls": [],
    "languages": [
      "eng"
    ],
    "country": "ca",
    "isGeoBlocked": false
  },
  {
    "nanoid": "w6ttDNPMaglKeI",
    "name": "HT Spor",
    "stream_urls": [],
    "youtube_urls": [
      "https://www.youtube-nocookie.com/embed/ih2KAtA50I4"
    ],
    "languages": [
      "tur"
    ],
    "country": "tr",
    "isGeoBlocked": false
  },
  {
    "nanoid": "GV38pwWqigwkoF",
    "name": "HTV Thể thao",
    "stream_urls": [
      "https://live.fptplay53.net/epzhd1/htvcthethao_vhls.smil/chunklist.m3u8"
    ],
    "youtube_urls": [],
    "languages": [
      "vie"
    ],
    "country": "vn",
    "isGeoBlocked": false
  },
  {
    "nanoid": "YJ0VLCpIyYcZ5V",
    "name": "InTrouble",
    "stream_urls": [
      "https://amg00861-terncloud-amg00861c6-cineverse-us-964.playouts.now.amagi.tv/playlist/amg00861-terninternationalfast-introublehd-cineverseus/playlist.m3u8",
      "https://amg00861-amg00861c6-stirr-us-8229.playouts.now.amagi.tv/playlist.m3u8"
    ],
    "youtube_urls": [],
    "languages": [
      "eng"
    ],
    "country": "nl",
    "isGeoBlocked": false
  },
  {
    "nanoid": "KPtXyd5nRjav8n",
    "name": "KCMN-LD6",
    "stream_urls": [
      "https://cdn-uw2-prod.tsv2.amagi.tv/linear/amg02873-kravemedia-mtrspt1-distrotv/playlist.m3u8"
    ],
    "youtube_urls": [],
    "languages": [
      "eng"
    ],
    "country": "us",
    "isGeoBlocked": false
  },
  {
    "nanoid": "wry8kPUipkC3Ee",
    "name": "KTV Sport",
    "stream_urls": [
      "https://kwtspta.cdn.mangomolo.com/sp/smil:sp.stream.smil/chunklist.m3u8"
    ],
    "youtube_urls": [],
    "languages": [
      "eng"
    ],
    "country": "kw",
    "isGeoBlocked": false
  },
  {
    "nanoid": "u6GFOdoySx8qXc",
    "name": "KTV Sport Plus",
    "stream_urls": [
      "https://kwtsplta.cdn.mangomolo.com/spl/smil:spl.stream.smil/chunklist.m3u8"
    ],
    "youtube_urls": [],
    "languages": [
      "ara"
    ],
    "country": "kw",
    "isGeoBlocked": false
  },
  {
    "nanoid": "wiIsgplTccLk32",
    "name": "Lacrosse TV",
    "stream_urls": [
      "https://1840769862.rsc.cdn77.org/FTF/LSN_SCTE.m3u8"
    ],
    "youtube_urls": [],
    "languages": [
      "eng"
    ],
    "country": "us",
    "isGeoBlocked": false
  },
  {
    "nanoid": "1eV4O1qgcFehgA",
    "name": "LaLiga Hypermotion",
    "stream_urls": [
      "https://latam-cache-sv2-cdn.latamlive.net/LA_LIGA_SMARTBANK_IP_ENC_LIVE/index.m3u8"
    ],
    "youtube_urls": [],
    "languages": [
      "eng"
    ],
    "country": "es",
    "isGeoBlocked": false
  },
  {
    "nanoid": "H7YKUTmTDg1xzR",
    "name": "M-Net Sport",
    "stream_urls": [
      "https://live.mnet.mk/hls/mnet-sport.m3u8"
    ],
    "youtube_urls": [],
    "languages": [
      "mkd"
    ],
    "country": "mk",
    "isGeoBlocked": false
  },
  {
    "nanoid": "hRCPRwYpEDOZ41",
    "name": "MadeinBO TV",
    "stream_urls": [
      "https://srvx1.selftv.video/dmchannel/live/playlist.m3u8"
    ],
    "youtube_urls": [],
    "languages": [
      "ita"
    ],
    "country": "it",
    "isGeoBlocked": false
  },
  {
    "nanoid": "BIe1OnuqGUuA60",
    "name": "MLB Channel",
    "stream_urls": [
      "https://pb-2y9ox4r1fy550.akamaized.net/playlist.m3u8",
      "https://aegis-cloudfront-1.tubi.video/36ef2f9d-7100-4c4d-b41a-dbf41ab7e461/playlist.m3u8"
    ],
    "youtube_urls": [],
    "languages": [
      "eng"
    ],
    "country": "us",
    "isGeoBlocked": true
  },
  {
    "nanoid": "WjzlJmHsxUPxpZ",
    "name": "MNB Sport",
    "stream_urls": [
      "https://live.mnb.mn/hls/mnb_sport.stream.m3u8"
    ],
    "youtube_urls": [],
    "languages": [
      "mon"
    ],
    "country": "mn",
    "isGeoBlocked": false
  },
  {
    "nanoid": "VV5nh58QSIjuA6",
    "name": "More Than Sports TV",
    "stream_urls": [
      "https://mts1.iptv-playoutcenter.de/mts/mts-web/playlist.m3u8"
    ],
    "youtube_urls": [],
    "languages": [
      "deu"
    ],
    "country": "de",
    "isGeoBlocked": false
  },
  {
    "nanoid": "Da460ZcoL5SJKT",
    "name": "Multivisión Sports",
    "stream_urls": [
      "https://stream.digitalgt.com:3605/live/multivisionsportslive.m3u8"
    ],
    "youtube_urls": [],
    "languages": [
      "spa"
    ],
    "country": "gt",
    "isGeoBlocked": false
  },
  {
    "nanoid": "RcmUVMpfqvK186",
    "name": "NBA TV",
    "stream_urls": [
      "https://amg00556-amg00556c3-firetv-us-6060.playouts.now.amagi.tv/playlist.m3u8",
      "https://pb-5pdyic0cu7tri.akamaized.net/NBA.m3u8"
    ],
    "youtube_urls": [],
    "languages": [
      "eng"
    ],
    "country": "us",
    "isGeoBlocked": true
  },
  {
    "nanoid": "mgCBsRrwyHVP1v",
    "name": "NBC Sports NOW",
    "stream_urls": [
      "https://d4whmvwm0rdvi.cloudfront.net/10007/99993008/hls/master.m3u8?ads.xumo_channelId=99993008",
      "https://d1m1xk35ma8qfl.cloudfront.net/master.m3u8",
      "https://xumo-xumoent-vc-122-sjv70.fast.nbcuni.com/live/master.m3u8"
    ],
    "youtube_urls": [],
    "languages": [
      "eng"
    ],
    "country": "us",
    "isGeoBlocked": false
  },
  {
    "nanoid": "tvm8YPiEknLHQu",
    "name": "NFL Channel",
    "stream_urls": [
      "https://pb-we3ltka9xobj6.akamaized.net/master.m3u8"
    ],
    "youtube_urls": [],
    "languages": [
      "eng"
    ],
    "country": "us",
    "isGeoBlocked": true
  },
  {
    "nanoid": "iqW7NImquoQlAB",
    "name": "NHRA TV",
    "stream_urls": [
      "https://d265y4sk8257lt.cloudfront.net/nh.m3u8",
      "https://aegis-cloudfront-1.tubi.video/b8c5eb48-349b-454f-9625-63911ee923f5/playlist.m3u8"
    ],
    "youtube_urls": [],
    "languages": [
      "eng"
    ],
    "country": "us",
    "isGeoBlocked": false
  },
  {
    "nanoid": "g2M151IR177r4N",
    "name": "Nudge Sports Channel",
    "stream_urls": [
      "https://streams.comclark.com/live_input/nudge_sports/playlist.m3u8"
    ],
    "youtube_urls": [],
    "languages": [
      "eng"
    ],
    "country": "ph",
    "isGeoBlocked": false
  },
  {
    "nanoid": "yxyIFaB4Q9mpks",
    "name": "Oman Sports TV",
    "stream_urls": [
      "https://partneta.cdn.mgmlcdn.com/omsport/smil:omsport.stream.smil/chunklist.m3u8"
    ],
    "youtube_urls": [],
    "languages": [
      "eng"
    ],
    "country": "om",
    "isGeoBlocked": false
  },
  {
    "nanoid": "1s9iqdlMC7cMrp",
    "name": "Pac 12 Insider",
    "stream_urls": [
      "https://pac12-roku-us.amagi.tv/playlist.m3u8",
      "https://pac12-samsungus.amagi.tv/playlist.m3u8",
      "https://pac12-vizio.amagi.tv/playlist.m3u8"
    ],
    "youtube_urls": [],
    "languages": [
      "eng"
    ],
    "country": "us",
    "isGeoBlocked": false
  },
  {
    "nanoid": "4R8avfl25GTImU",
    "name": "Persiana Fight",
    "stream_urls": [
      "https://fighthls.persiana.live/hls/stream.m3u8"
    ],
    "youtube_urls": [],
    "languages": [
      "fas"
    ],
    "country": "fr",
    "isGeoBlocked": false
  },
  {
    "nanoid": "Rkk04fiUCPkcpz",
    "name": "PGA Tour",
    "stream_urls": [
      "https://pb-783hpus5r91wv.akamaized.net/playlist.m3u8",
      "https://aegis-cloudfront-1.tubi.video/9c59800e-fa9a-4539-b8e5-5769918e7c5a/playlist.m3u8"
    ],
    "youtube_urls": [],
    "languages": [
      "eng"
    ],
    "country": "us",
    "isGeoBlocked": true
  },
  {
    "nanoid": "Zv1phHWvbz0bE7",
    "name": "Poker Go",
    "stream_urls": [
      "https://aegis-cloudfront-1.tubi.video/b474c2bb-b34d-4c53-a94b-c4ffe884563c/playlist.m3u8",
      "https://linear-426.frequency.stream/dist/xumo/426/hls/master/playlist.m3u8"
    ],
    "youtube_urls": [],
    "languages": [
      "eng"
    ],
    "country": "us",
    "isGeoBlocked": false
  },
  {
    "nanoid": "vX2Vm81TXt010f",
    "name": "Premier Sports",
    "stream_urls": [
      "https://amg19223-amg19223c3-amgplt0351.playout.now3.amagi.tv/playlist/amg19223-amg19223c3-amgplt0351/playlist.m3u8"
    ],
    "youtube_urls": [],
    "languages": [
      "eng"
    ],
    "country": "ph",
    "isGeoBlocked": false
  },
  {
    "nanoid": "ZSj74UmnkvuvdN",
    "name": "Premier Sports 2",
    "stream_urls": [
      "https://amg19223-amg19223c4-amgplt0351.playout.now3.amagi.tv/playlist/amg19223-amg19223c4-amgplt0351/playlist.m3u8"
    ],
    "youtube_urls": [],
    "languages": [
      "eng"
    ],
    "country": "ph",
    "isGeoBlocked": false
  },
  {
    "nanoid": "hliOSpRjIJIon0",
    "name": "PRO Sport International",
    "stream_urls": [
      "https://proshls.wns.live/hls/stream.m3u8"
    ],
    "youtube_urls": [],
    "languages": [
      "fas"
    ],
    "country": "my",
    "isGeoBlocked": false
  },
  {
    "nanoid": "RlDh4IHVR4WpZw",
    "name": "QazSport",
    "stream_urls": [
      "https://qazsporttv-stream.qazcdn.com/qazsporttv/qazsporttv/playlist.m3u8"
    ],
    "youtube_urls": [],
    "languages": [
      "kaz"
    ],
    "country": "kz",
    "isGeoBlocked": false
  },
  {
    "nanoid": "7TX9VjMY1i891b",
    "name": "QSVS: Top Calcio 24",
    "stream_urls": [],
    "youtube_urls": [
      "https://www.youtube-nocookie.com/embed/smcQvzsh5Qo"
    ],
    "languages": [
      "ita"
    ],
    "country": "it",
    "isGeoBlocked": false
  },
  {
    "nanoid": "PgSQJkjlJAZPaq",
    "name": "RACER International",
    "stream_urls": [
      "https://amg00378-mavtv-amg00378c2-rakuten-us-1048.playouts.now.amagi.tv/playlist/amg00378-mavtvfast-motorsportsnetwork-rakutenus/playlist.m3u8"
    ],
    "youtube_urls": [],
    "languages": [
      "eng"
    ],
    "country": "pl",
    "isGeoBlocked": false
  },
  {
    "nanoid": "eJrCmsSX7xmegj",
    "name": "Racer Network",
    "stream_urls": [
      "https://amg00378-mavtv-amg00378c2-samsung-nz-1791.playouts.now.amagi.tv/playlist/amg00378-mavtvfast-motorsportsnetwork-samsungnz/playlist.m3u8"
    ],
    "youtube_urls": [],
    "languages": [
      "eng"
    ],
    "country": "us",
    "isGeoBlocked": false
  },
  {
    "nanoid": "Z4MMDRIAr3Lbyf",
    "name": "RACER Select",
    "stream_urls": [
      "https://d85qrcmltdfp8.cloudfront.net/MAVTV_Select.m3u8"
    ],
    "youtube_urls": [],
    "languages": [
      "eng"
    ],
    "country": "us",
    "isGeoBlocked": false
  },
  {
    "nanoid": "jHe1OEHTcksowX",
    "name": "Red Bull TV AU",
    "stream_urls": [
      "https://db34cc6127ac459db55cab5f97cd66b9.mediatailor.us-west-2.amazonaws.com/v1/master/ba62fe743df0fe93366eba3a257d792884136c7f/LINEAR-680-WORBAUENFAST-WHALETVPLUS/680/whaletvplus/hls/master/playlist.m3u8"
    ],
    "youtube_urls": [],
    "languages": [
      "eng"
    ],
    "country": "at",
    "isGeoBlocked": false
  },
  {
    "nanoid": "qSTI0JjIhB6uCt",
    "name": "Red Bull TV BR",
    "stream_urls": [
      "https://d03ae6b5c6724c24867e97a3dc04934a.mediatailor.us-west-2.amazonaws.com/v1/master/ba62fe743df0fe93366eba3a257d792884136c7f/LINEAR-1026-WORBBRPTFAST-WHALETVPLUS/1026/hls/master/playlist.m3u8"
    ],
    "youtube_urls": [],
    "languages": [
      "por"
    ],
    "country": "at",
    "isGeoBlocked": false
  },
  {
    "nanoid": "CFer2v8709wxRy",
    "name": "Red Bull TV ES",
    "stream_urls": [
      "https://886bd3fbc782459f8de7555d32d7e9ce.mediatailor.us-west-2.amazonaws.com/v1/master/ba62fe743df0fe93366eba3a257d792884136c7f/LINEAR-957-WORBLATAMESFAST-WHALETVPLUS/957/whaletvplus/hls/master/playlist.m3u8"
    ],
    "youtube_urls": [],
    "languages": [
      "spa"
    ],
    "country": "at",
    "isGeoBlocked": false
  },
  {
    "nanoid": "znLSEaZWfm2KZE",
    "name": "Red Bull TV SD",
    "stream_urls": [
      "https://rbmn-live.akamaized.net/hls/live/590964/BoRB-AT/master_3360.m3u8"
    ],
    "youtube_urls": [],
    "languages": [
      "eng"
    ],
    "country": "at",
    "isGeoBlocked": false
  },
  {
    "nanoid": "RV6yi21ilw5X2f",
    "name": "Red Bull TV US",
    "stream_urls": [
      "https://0b73ace69ebb45eaa249bb87837cb958.mediatailor.us-west-2.amazonaws.com/v1/master/ba62fe743df0fe93366eba3a257d792884136c7f/LINEAR-644-WORBUSENFAST-LG_US/644/lgtv/hls/master/playlist.m3u8"
    ],
    "youtube_urls": [],
    "languages": [
      "eng"
    ],
    "country": "at",
    "isGeoBlocked": false
  },
  {
    "nanoid": "DlnA3363JGvPGt",
    "name": "RightNow TV",
    "stream_urls": [
      "https://a-cdn.klowdtv.com/live2/rightnowtv_720p/playlist.m3u8",
      "https://2-fss-1.streamhoster.com/pl_154/amlst:205448-2145652/rightnowtv.m3u8"
    ],
    "youtube_urls": [],
    "languages": [
      "eng"
    ],
    "country": "us",
    "isGeoBlocked": false
  },
  {
    "nanoid": "SIki0bxRn3r6qL",
    "name": "Sport Italia",
    "stream_urls": [
      "https://amg01370-italiansportcom-sportitalia-rakuten-3hmdb.amagi.tv/hls/amagi_hls_data_rakutenAA-sportitalia-rakuten/CDN/master.m3u8",
      "https://sportsitalia-samsungitaly.amagi.tv/playlist.m3u8"
    ],
    "youtube_urls": [],
    "languages": [
      "ita"
    ],
    "country": "it",
    "isGeoBlocked": false
  },
  {
    "nanoid": "QwsKOZxcusvvv2",
    "name": "SportsGrid",
    "stream_urls": [
      "https://amg00315-sportsgrid-firetv.amagi.tv/playlist.m3u8",
      "https://sportsgrid-plex.amagi.tv/playlist.m3u8",
      "https://sportsgrid-samsungus.amagi.tv/playlist.m3u8",
      "https://sportsgrid-klowdtv.amagi.tv/playlist.m3u8"
    ],
    "youtube_urls": [],
    "languages": [
      "eng"
    ],
    "country": "us",
    "isGeoBlocked": false
  },
  {
    "nanoid": "SoJfGpE8xBZiUl",
    "name": "Stadium",
    "stream_urls": [
      "https://wurl120sports.global.transmit.live/hls/679a907dce42a042c23ace37/v1/stadium_gracenote/samsung_us/latest/main/hls/playlist.m3u8",
      "https://aegis-cloudfront-1.tubi.video/74681dcc-e6d0-4add-ad67-a22ad9c152e6/playlist.m3u8"
    ],
    "youtube_urls": [],
    "languages": [
      "eng"
    ],
    "country": "us",
    "isGeoBlocked": false
  },
  {
    "nanoid": "TnYj2ZiJkibGxp",
    "name": "Suspilne. Sport",
    "stream_urls": [
      "https://cdnua05.hls.tv/934/hls/8743361621b245838bee193c9ec28322/4856/stream.m3u8"
    ],
    "youtube_urls": [],
    "languages": [
      "ukr"
    ],
    "country": "ua",
    "isGeoBlocked": false
  },
  {
    "nanoid": "WY8xpPtdqP8OfL",
    "name": "Swerve Combat",
    "stream_urls": [
      "https://linear-253.frequency.stream/mt/roku/253/hls/master/playlist.m3u8",
      "https://linear-253.frequency.stream/dist/stirr/253/hls/master/playlist.m3u8",
      "https://linear-253.frequency.stream/dist/xumo/253/hls/master/playlist.m3u8"
    ],
    "youtube_urls": [],
    "languages": [
      "eng"
    ],
    "country": "us",
    "isGeoBlocked": false
  },
  {
    "nanoid": "4Me0RU4rvtok1Y",
    "name": "Tele Rebelde",
    "stream_urls": [
      "https://tv.picta.cu/telerebelde/telerebelde_1.m3u8"
    ],
    "youtube_urls": [],
    "languages": [
      "spa"
    ],
    "country": "cu",
    "isGeoBlocked": false
  },
  {
    "nanoid": "okKQ8KDUVqmzeR",
    "name": "Teletrak",
    "stream_urls": [
      "https://unlimited6-cl.dps.live/sportinghd/sportinghd.smil/playlist.m3u8"
    ],
    "youtube_urls": [],
    "languages": [
      "spa"
    ],
    "country": "cl",
    "isGeoBlocked": false
  },
  {
    "nanoid": "XdwrocdV5KOMCW",
    "name": "Tennis Channel",
    "stream_urls": [
      "https://cdn-uw2-prod.tsv2.amagi.tv/linear/amg01444-tennischannelth-tennischnlintl-lggb/playlist.m3u8"
    ],
    "youtube_urls": [],
    "languages": [
      "eng"
    ],
    "country": "us",
    "isGeoBlocked": false
  },
  {
    "nanoid": "oiFEO2uBrrWk1f",
    "name": "Tigo Sports TV El Salvador",
    "stream_urls": [
      "https://channel03.tigosports.com.sv/out/v1/31f36d52d558475ca18799d8ca5e4b40/index.m3u8"
    ],
    "youtube_urls": [],
    "languages": [
      "spa"
    ],
    "country": "sv",
    "isGeoBlocked": false
  },
  {
    "nanoid": "vtSycR8Kbn52EY",
    "name": "TJK TV",
    "stream_urls": [
      "https://tjktv-live.tjk.org/tjktv.m3u8"
    ],
    "youtube_urls": [
      "https://www.youtube-nocookie.com/embed/g89RQMJtK6E"
    ],
    "languages": [
      "tur"
    ],
    "country": "tr",
    "isGeoBlocked": false
  },
  {
    "nanoid": "MF8dCK1EmeF821",
    "name": "Tour Spot TV",
    "stream_urls": [
      "https://fox.hostlagarto.com:8081/toursporttv/playlist.m3u8"
    ],
    "youtube_urls": [],
    "languages": [
      "spa"
    ],
    "country": "do",
    "isGeoBlocked": false
  },
  {
    "nanoid": "PoFjoPeTQSvrgP",
    "name": "TR Sport",
    "stream_urls": [
      "https://livetr.teleromagna.it/mia/live/playlist.m3u8"
    ],
    "youtube_urls": [],
    "languages": [
      "ita"
    ],
    "country": "it",
    "isGeoBlocked": false
  },
  {
    "nanoid": "KqqtNJzLvYMM8F",
    "name": "Trace Sports Stars",
    "stream_urls": [
      "https://tracesportstars-klowdtv.amagi.tv/playlist.m3u8",
      "https://amg01131-tracetv-amg01131c2-stirr-us-4392.playouts.now.amagi.tv/playlist.m3u8"
    ],
    "youtube_urls": [],
    "languages": [
      "eng"
    ],
    "country": "fr",
    "isGeoBlocked": false
  },
  {
    "nanoid": "P1nM4FBKgqLCGY",
    "name": "TSN The Ocho",
    "stream_urls": [
      "https://d3pnbvng3bx2nj.cloudfront.net/v1/master/3722c60a815c199d9c0ef36c5b73da68a62b09d1/cc-rds8g35qfqrnv/TSN_The_Ocho.m3u8"
    ],
    "youtube_urls": [],
    "languages": [
      "eng"
    ],
    "country": "ca",
    "isGeoBlocked": false
  },
  {
    "nanoid": "aE41LbUT8Fnd7w",
    "name": "Turf Movil",
    "stream_urls": [
      "https://tvturf4.janus.cl/playlist/stream.m3u8?d=w&id="
    ],
    "youtube_urls": [],
    "languages": [
      "spa"
    ],
    "country": "cl",
    "isGeoBlocked": false
  },
  {
    "nanoid": "lX8llbHeMkmnOY",
    "name": "TVR Sport",
    "stream_urls": [
      "https://tvr-sport.lg.mncdn.com/tvrsport/smil:tvrsport.smil/chunklist_b5160000.m3u8"
    ],
    "youtube_urls": [],
    "languages": [
      "ron"
    ],
    "country": "ro",
    "isGeoBlocked": false
  },
  {
    "nanoid": "OS0pJpfqrL4sYH",
    "name": "TVRI Sport",
    "stream_urls": [
      "https://ott-balancer.tvri.go.id/live/eds/SportHD/hls/SportHD.m3u8"
    ],
    "youtube_urls": [],
    "languages": [
      "ind"
    ],
    "country": "id",
    "isGeoBlocked": false
  },
  {
    "nanoid": "3vI6OVnBudkJbF",
    "name": "TVS Bowling Network",
    "stream_urls": [
      "https://rpn.bozztv.com/gusa/gusa-tvsbowling/index.m3u8"
    ],
    "youtube_urls": [],
    "languages": [
      "eng"
    ],
    "country": "us",
    "isGeoBlocked": false
  },
  {
    "nanoid": "weRNAtNJMdiRC8",
    "name": "TVS Boxing",
    "stream_urls": [
      "https://rpn.bozztv.com/gusa/gusa-tvsboxing/index.m3u8"
    ],
    "youtube_urls": [],
    "languages": [
      "eng"
    ],
    "country": "us",
    "isGeoBlocked": false
  },
  {
    "nanoid": "Wbrb2C2Gun42Sy",
    "name": "TVS Classic Sports",
    "stream_urls": [
      "https://rpn.bozztv.com/gusa/gusa-tvs/index.m3u8"
    ],
    "youtube_urls": [],
    "languages": [
      "eng"
    ],
    "country": "us",
    "isGeoBlocked": false
  },
  {
    "nanoid": "MRDwiz0Mw0bVZ5",
    "name": "TVS Sports",
    "stream_urls": [
      "https://rpn.bozztv.com/gusa/gusa-tvssports/index.m3u8"
    ],
    "youtube_urls": [],
    "languages": [
      "eng"
    ],
    "country": "us",
    "isGeoBlocked": false
  },
  {
    "nanoid": "uxa3RChSlTbz84",
    "name": "TVS Sports Bureau",
    "stream_urls": [
      "https://rpn.bozztv.com/gusa/gusa-tvssportsbureau/index.m3u8"
    ],
    "youtube_urls": [],
    "languages": [
      "eng"
    ],
    "country": "us",
    "isGeoBlocked": false
  },
  {
    "nanoid": "eIJ4L4aV4I4YRC",
    "name": "TVS Turbo",
    "stream_urls": [
      "https://rpn.bozztv.com/gusa/gusa-tvsturbo/index.m3u8"
    ],
    "youtube_urls": [],
    "languages": [
      "eng"
    ],
    "country": "us",
    "isGeoBlocked": false
  },
  {
    "nanoid": "beAXn8CiW6Z5Te",
    "name": "TVS Women Sports",
    "stream_urls": [
      "https://rpn.bozztv.com/gusa/gusa-tvswsn/index.m3u8"
    ],
    "youtube_urls": [],
    "languages": [
      "eng"
    ],
    "country": "us",
    "isGeoBlocked": false
  },
  {
    "nanoid": "7HA7nsSxvggwxL",
    "name": "Unbeaten Sports Channel",
    "stream_urls": [
      "https://d1t5afz6qed3xk.cloudfront.net/Unbeaten.m3u8",
      "https://unbeaten-tcl.amagi.tv/playlist.m3u8"
    ],
    "youtube_urls": [],
    "languages": [
      "eng"
    ],
    "country": "us",
    "isGeoBlocked": false
  },
  {
    "nanoid": "qoUkakDtbgDtaT",
    "name": "VITAL Drive",
    "stream_urls": [
      "https://autopilot.catcast.tv/content/37909/index.m3u8",
      "https://tv.a21network.ru/stream/37909/index.m3u8"
    ],
    "youtube_urls": [],
    "languages": [
      "rus"
    ],
    "country": "ru",
    "isGeoBlocked": false
  },
  {
    "nanoid": "jZEkpGlt5AGs91",
    "name": "WCW",
    "stream_urls": [],
    "youtube_urls": [
      "https://www.youtube-nocookie.com/embed/SIBP7u0tDJY"
    ],
    "languages": [
      "eng"
    ],
    "country": "us",
    "isGeoBlocked": false
  },
  {
    "nanoid": "d0G4zB6FBlCOOM",
    "name": "Willow Sports",
    "stream_urls": [
      "https://amg01269-amg01269c1-firetv-us-5377.playouts.now.amagi.tv/playlist.m3u8",
      "https://amg01269-amg01269c1-distrotv-us-5379.playouts.now.amagi.tv/playlist/amg01269-willowtvfast-willowplus-distrotvus/playlist.m3u8",
      "https://d36r8jifhgsk5j.cloudfront.net/Willow_TV.m3u8"
    ],
    "youtube_urls": [],
    "languages": [
      "eng"
    ],
    "country": "us",
    "isGeoBlocked": true
  },
  {
    "nanoid": "Rbcaed64dSHjvH",
    "name": "World of Freesports",
    "stream_urls": [
      "https://mainstreammedia-worldoffreesportsintl-rakuten.amagi.tv/playlist.m3u8",
      "https://mainstreammedia-worldoffreesportsintl-rakuten.amagi.tv/hls/amagi_hls_data_rakutenAA-mainstreammediafreesportsintl-rakuten/CDN/master.m3u8"
    ],
    "youtube_urls": [],
    "languages": [
      "deu"
    ],
    "country": "de",
    "isGeoBlocked": false
  },
  {
    "nanoid": "X8yK2ahG1lHzY9",
    "name": "World Poker Tour",
    "stream_urls": [
      "https://pb-41uwb26l8gvwx.akamaized.net/World_Poker_Tour.m3u8",
      "https://d2e00kr7m9coe4.cloudfront.net/scheduler/scheduleMaster/406.m3u8",
      "https://amg00218-wptenterprisesi-worldpokertour-xumo-us.amagi.tv/playlist.m3u8",
      "https://amg00218-wptenterprisesi-worldpokertour-klowdtv-5619e.amagi.tv/playlist/amg00218-wptenterprisesi-worldpokertour-klowdtv/playlist.m3u8",
      "https://d39g1vxj2ef6in.cloudfront.net/v1/master/3fec3e5cac39a52b2132f9c66c83dae043dc17d4/prod-rakuten-stitched/playlist.m3u8?ads.xumo_channelId=88883102"
    ],
    "youtube_urls": [],
    "languages": [
      "eng"
    ],
    "country": "us",
    "isGeoBlocked": true
  },
  {
    "nanoid": "EZYzbbetjgxX2q",
    "name": "World Poker Tour 1",
    "stream_urls": [],
    "youtube_urls": [
      "https://www.youtube-nocookie.com/embed/t1GodAvci_g"
    ],
    "languages": [
      "eng"
    ],
    "country": "us",
    "isGeoBlocked": false
  },
  {
    "nanoid": "CCEdL436rIG1E6",
    "name": "World Poker Tour 2",
    "stream_urls": [],
    "youtube_urls": [
      "https://www.youtube-nocookie.com/embed/AatxkgXuaBI"
    ],
    "languages": [
      "eng"
    ],
    "country": "us",
    "isGeoBlocked": false
  },
  {
    "nanoid": "8Ndns6qOA3E0TP",
    "name": "WWE",
    "stream_urls": [],
    "youtube_urls": [
      "https://www.youtube-nocookie.com/embed/-b4UEAGPBBQ"
    ],
    "languages": [
      "eng"
    ],
    "country": "us",
    "isGeoBlocked": false
  },
  {
    "nanoid": "KfPyDEuOOc6z6o",
    "name": "WWE Vault",
    "stream_urls": [],
    "youtube_urls": [
      "https://www.youtube-nocookie.com/embed/yRc2z0F_8uE"
    ],
    "languages": [
      "eng"
    ],
    "country": "us",
    "isGeoBlocked": false
  },
  {
    "nanoid": "PnYs28KZYftvil",
    "name": "Астрахань.Ru Sport",
    "stream_urls": [
      "https://streaming.astrakhan.ru/astrakhanrusporthd/playlist.m3u8"
    ],
    "youtube_urls": [],
    "languages": [
      "rus"
    ],
    "country": "ru",
    "isGeoBlocked": false
  },
  {
    "nanoid": "yxXfCHd5uHQMJD",
    "name": "Беларусь 5",
    "stream_urls": [
      "https://ngtrk.dc.beltelecom.by/ngtrk/smil:belarus5.smil/playlist.m3u8"
    ],
    "youtube_urls": [],
    "languages": [
      "rus"
    ],
    "country": "by",
    "isGeoBlocked": false
  }
]
